[
    {
        "@type": "DataType",
        "@context": "https://schema.host/",
        "@id": "https://schema.host/Text",
        "name": "Text",
        "description": "A string of text",
        "parent": "https://schema.host/DataType"
    },
    {
        "@type": "DataType",
        "@context": "https://schema.host/",
        "@id": "https://schema.host/URL",
        "name": "URL",
        "description": "A W3C valid URL",
        "parent": "https://schema.host/DataType"
    },
    {
        "@type": "DataType",
        "@context":"https://schema.host/",
        "@id": "https://schema.host/Cardinal",
        "name": "Cardinal",
        "description": "An indicator of cardinality",
        "parent": "https://schema.host/DataType",
        "enumerator": [
            "1",
            "0..1",
            "0..n",
            "1..n"
        ]
    },
    {
        "@type": "DataType",
        "@context":"https://schema.host/",
        "@id": "https://schema.host/Number",
        "name": "Number",
        "parent": "https://schema.host/DataType",
        "description": "Validates that something is a Number."
    },
    {
        "@type": "DataType",
        "@context":"https://schema.host/",
        "@id": "https://schema.host/Boolean",
        "name": "Boolean",
        "description": "True, or false",
        "parent": "https://schema.host/DataType",
        "enumerator": [
            "true",
            "false"
        ]
    },
    {
        "@type": "DataType",
        "@context":"https://schema.host/",
        "@id": "https://schema.host/DateTime",
        "name": "DateTime",
        "parent": "https://schema.host/DataType",
        "description": "ISO8601 Date Time"
    },
    {
        "@type": "DataType",
        "@context":"https://schema.host/",
        "@id": "https://schema.host/Date",
        "name": "Date",
        "parent": "https://schema.host/DataType",
        "description": "ISO8601 Date"
    },
    {
        "@type": "DataType",
        "@context":"https://schema.host/",
        "@id": "https://schema.host/JSON",
        "name": "JSON",
        "parent": "https://schema.host/DataType",
        "description": "JSON data"
    }
]