{
  "@type": "Schema",
  "@context": "https://schema.host/",
  "@id": "https://schema.host/DataType",
  "name": "DataType",
  "description": "generic microdata schema for any datatype",
  "validator": "https://schema.host/DataType/index.mjs",
  "parent": "https://schema.host/Schema",
  "property": [
    {
      "@type": "Property",
      "@context": "https://schema.host/",
      "name": "url",
      "description": "The type of the datatype",
      "cardinality": "1",
      "type": "https://schema.host/URL"
    },
    {
      "@type": "Property",
      "@context": "https://schema.host/",
      "name": "description",
      "type": "https://schema.host/Text",
      "cardinality": 1,
      "description": "A description of the DataType."
    }
  ]
}