{
  "@type": "Schema",
  "@context": "https://schema.host/",
  "@id": "https://schema.host/DataType",
  "name": "DataType",
  "description": "A data type with optional format validation.",
  "parent": "https://schema.host/Schema",
  "property": [
    {
      "@type": "Property",
      "@context": "https://schema.host/",
      "name": "name",
      "description": "The name of the data type.",
      "cardinality": "1..1",
      "type": "https://schema.host/Text"
    },
    {
      "@type": "Property",
      "@context": "https://schema.host/",
      "name": "description",
      "description": "A description of the data type.",
      "cardinality": "0..1",
      "type": "https://schema.host/Text"
    },
    {
      "@type": "Property",
      "@context": "https://schema.host/",
      "name": "parent",
      "description": "The URL of the parent data type.",
      "cardinality": "0..1",
      "type": "https://schema.host/URL"
    },
    {
      "@type": "Property",
      "@context": "https://schema.host/",
      "name": "matches",
      "description": "A regular expression that values of this type must match for format validation.",
      "cardinality": "0..1",
      "type": "https://schema.host/Text"
    }
  ]
}